namahate/__init__.py
namahate-0.1.1.dist-info/METADATA
namahate-0.1.1.dist-info/WHEEL
namahate-0.1.1.dist-info/entry_points.txt
namahate-0.1.1.dist-info/RECORD
