Metadata-Version: 2.3
Name: namahate
Version: 0.1.1
Summary: Add your description here
Author: Sachidananda Maiya
License: MIT License
Requires-Python: >=3.13
Requires-Dist: httpx>=0.27.2
